<annotationInfo>
<annotationInfo>
<item  id="54" filename="../src/Conv2d/Conv2d.cpp" linenumber="29" name="lhs_V" contextFuncName="Conv2D" moduleName="Conv2D" rtlName="lhs_V_fu_475_p1" latency="0" BRAM="-1" DSP="-1" FF="-1" LUT="-1" fileDirectory="D:\code\git\HLS\HLS"><\/item>
<item  id="55" filename="../src/Conv2d/Conv2d.cpp" linenumber="29" name="rhs_V" contextFuncName="Conv2D" moduleName="Conv2D" rtlName="rhs_V_fu_479_p1" latency="0" BRAM="-1" DSP="-1" FF="-1" LUT="-1" fileDirectory="D:\code\git\HLS\HLS"><\/item>
<item  id="56" filename="../src/Conv2d/Conv2d.cpp" linenumber="29" name="ret_V" contextFuncName="Conv2D" moduleName="Conv2D" rtlName="ret_V_fu_483_p2" latency="0" BRAM="-1" DSP="-1" FF="0" LUT="9" fileDirectory="D:\code\git\HLS\HLS"><\/item>
<item  id="59" filename="../src/Conv2d/Conv2d.cpp" linenumber="29" name="tmp_cast" contextFuncName="Conv2D" moduleName="Conv2D" rtlName="tmp_cast_fu_501_p1" latency="0" BRAM="-1" DSP="-1" FF="-1" LUT="-1" fileDirectory="D:\code\git\HLS\HLS"><\/item>
<item  id="60" filename="../src/Conv2d/Conv2d.cpp" linenumber="29" name="ret_V_2_tr" contextFuncName="Conv2D" moduleName="Conv2D" rtlName="ret_V_2_tr_fu_505_p2" latency="0" BRAM="-1" DSP="-1" FF="0" LUT="11" fileDirectory="D:\code\git\HLS\HLS"><\/item>
<item  id="61" filename="../src/Conv2d/Conv2d.cpp" linenumber="29" name="ret_V_2_tr_cast" contextFuncName="Conv2D" moduleName="Conv2D" rtlName="grp_fu_519_p0" latency="0" BRAM="-1" DSP="-1" FF="-1" LUT="-1" fileDirectory="D:\code\git\HLS\HLS"><\/item>
<item  id="62" filename="../src/Conv2d/Conv2d.cpp" linenumber="29" name="tmp_tr4" contextFuncName="Conv2D" moduleName="Conv2D" rtlName="tmp_tr4_fu_515_p1" latency="0" BRAM="-1" DSP="-1" FF="-1" LUT="-1" fileDirectory="D:\code\git\HLS\HLS"><\/item>
<item  id="63" filename="../src/Conv2d/Conv2d.cpp" linenumber="29" name="tmp_6" contextFuncName="Conv2D" moduleName="Conv2D" rtlName="Conv2D_sdiv_12s_9bkb_U1" latency="15" BRAM="-1" DSP="-1" FF="-1" LUT="-1" fileDirectory="D:\code\git\HLS\HLS"><\/item>
<item  id="64" filename="../src/Conv2d/Conv2d.cpp" linenumber="29" name="tmp_2_cast" contextFuncName="Conv2D" moduleName="Conv2D" rtlName="tmp_2_cast_fu_567_p1" latency="0" BRAM="-1" DSP="-1" FF="-1" LUT="-1" fileDirectory="D:\code\git\HLS\HLS"><\/item>
<item  id="65" filename="../src/Conv2d/Conv2d.cpp" linenumber="29" name="output_width" contextFuncName="Conv2D" moduleName="Conv2D" rtlName="output_width_fu_571_p2" latency="0" BRAM="-1" DSP="-1" FF="0" LUT="13" fileDirectory="D:\code\git\HLS\HLS"><\/item>
<item  id="66" filename="../src/Conv2d/Conv2d.cpp" linenumber="29" name="output_width_cast" contextFuncName="Conv2D" moduleName="Conv2D" rtlName="output_width_cast_fu_577_p1" latency="0" BRAM="-1" DSP="-1" FF="-1" LUT="-1" fileDirectory="D:\code\git\HLS\HLS"><\/item>
<item  id="67" filename="../src/Conv2d/Conv2d.cpp" linenumber="30" name="lhs_V_1" contextFuncName="Conv2D" moduleName="Conv2D" rtlName="lhs_V_1_fu_525_p1" latency="0" BRAM="-1" DSP="-1" FF="-1" LUT="-1" fileDirectory="D:\code\git\HLS\HLS"><\/item>
<item  id="68" filename="../src/Conv2d/Conv2d.cpp" linenumber="30" name="ret_V_2" contextFuncName="Conv2D" moduleName="Conv2D" rtlName="ret_V_2_fu_529_p2" latency="0" BRAM="-1" DSP="-1" FF="0" LUT="9" fileDirectory="D:\code\git\HLS\HLS"><\/item>
<item  id="69" filename="../src/Conv2d/Conv2d.cpp" linenumber="30" name="tmp_7_cast" contextFuncName="Conv2D" moduleName="Conv2D" rtlName="tmp_7_cast_fu_535_p1" latency="0" BRAM="-1" DSP="-1" FF="-1" LUT="-1" fileDirectory="D:\code\git\HLS\HLS"><\/item>
<item  id="70" filename="../src/Conv2d/Conv2d.cpp" linenumber="30" name="ret_V_5_tr" contextFuncName="Conv2D" moduleName="Conv2D" rtlName="ret_V_5_tr_fu_539_p2" latency="0" BRAM="-1" DSP="-1" FF="0" LUT="11" fileDirectory="D:\code\git\HLS\HLS"><\/item>
<item  id="71" filename="../src/Conv2d/Conv2d.cpp" linenumber="30" name="ret_V_5_tr_cast" contextFuncName="Conv2D" moduleName="Conv2D" rtlName="grp_fu_549_p0" latency="0" BRAM="-1" DSP="-1" FF="-1" LUT="-1" fileDirectory="D:\code\git\HLS\HLS"><\/item>
<item  id="72" filename="../src/Conv2d/Conv2d.cpp" linenumber="30" name="tmp_s" contextFuncName="Conv2D" moduleName="Conv2D" rtlName="Conv2D_sdiv_12s_9bkb_U2" latency="15" BRAM="-1" DSP="-1" FF="-1" LUT="-1" fileDirectory="D:\code\git\HLS\HLS"><\/item>
<item  id="73" filename="../src/Conv2d/Conv2d.cpp" linenumber="30" name="tmp_9_cast" contextFuncName="Conv2D" moduleName="Conv2D" rtlName="tmp_9_cast_fu_581_p1" latency="0" BRAM="-1" DSP="-1" FF="-1" LUT="-1" fileDirectory="D:\code\git\HLS\HLS"><\/item>
<item  id="74" filename="../src/Conv2d/Conv2d.cpp" linenumber="30" name="output_height" contextFuncName="Conv2D" moduleName="Conv2D" rtlName="output_height_fu_585_p2" latency="0" BRAM="-1" DSP="-1" FF="0" LUT="13" fileDirectory="D:\code\git\HLS\HLS"><\/item>
<item  id="75" filename="../src/Conv2d/Conv2d.cpp" linenumber="51" name="output_height_cast_c" contextFuncName="Conv2D" moduleName="Conv2D" rtlName="output_height_cast_c_fu_591_p1" latency="0" BRAM="-1" DSP="-1" FF="-1" LUT="-1" fileDirectory="D:\code\git\HLS\HLS"><\/item>
<item  id="76" filename="../src/Conv2d/Conv2d.cpp" linenumber="42" name="tmp_cast_cast" contextFuncName="Conv2D" moduleName="Conv2D" rtlName="tmp_cast_cast_fu_595_p1" latency="0" BRAM="-1" DSP="-1" FF="-1" LUT="-1" fileDirectory="D:\code\git\HLS\HLS"><\/item>
<item  id="77" filename="../src/Conv2d/Conv2d.cpp" linenumber="42" name="tmp_1_cast" contextFuncName="Conv2D" moduleName="Conv2D" rtlName="tmp_1_cast_fu_598_p1" latency="0" BRAM="-1" DSP="-1" FF="-1" LUT="-1" fileDirectory="D:\code\git\HLS\HLS"><\/item>
<item  id="78" filename="../src/Conv2d/Conv2d.cpp" linenumber="42" name="tmp_3_cast" contextFuncName="Conv2D" moduleName="Conv2D" rtlName="tmp_3_cast_fu_601_p1" latency="0" BRAM="-1" DSP="-1" FF="-1" LUT="-1" fileDirectory="D:\code\git\HLS\HLS"><\/item>
<item  id="79" filename="../src/Conv2d/Conv2d.cpp" linenumber="44" name="tmp_4_cast" contextFuncName="Conv2D" moduleName="Conv2D" rtlName="tmp_4_cast_fu_604_p1" latency="0" BRAM="-1" DSP="-1" FF="-1" LUT="-1" fileDirectory="D:\code\git\HLS\HLS"><\/item>
<item  id="80" filename="../src/Conv2d/Conv2d.cpp" linenumber="44" name="rhs_V_3_cast" contextFuncName="Conv2D" moduleName="Conv2D" rtlName="rhs_V_3_cast_fu_607_p1" latency="0" BRAM="-1" DSP="-1" FF="-1" LUT="-1" fileDirectory="D:\code\git\HLS\HLS"><\/item>
<item  id="81" filename="../src/Conv2d/Conv2d.cpp" linenumber="44" name="rhs_V_4_cast" contextFuncName="Conv2D" moduleName="Conv2D" rtlName="rhs_V_4_cast_fu_610_p1" latency="0" BRAM="-1" DSP="-1" FF="-1" LUT="-1" fileDirectory="D:\code\git\HLS\HLS"><\/item>
<item  id="82" filename="../src/Conv2d/Conv2d.cpp" linenumber="45" name="rhs_V_5_cast_cast" contextFuncName="Conv2D" moduleName="Conv2D" rtlName="rhs_V_5_cast_cast_fu_613_p1" latency="0" BRAM="-1" DSP="-1" FF="-1" LUT="-1" fileDirectory="D:\code\git\HLS\HLS"><\/item>
<item  id="83" filename="../src/Conv2d/Conv2d.cpp" linenumber="45" name="rhs_V_9_cast" contextFuncName="Conv2D" moduleName="Conv2D" rtlName="rhs_V_9_cast_fu_616_p1" latency="0" BRAM="-1" DSP="-1" FF="-1" LUT="-1" fileDirectory="D:\code\git\HLS\HLS"><\/item>
<item  id="84" filename="../src/Conv2d/Conv2d.cpp" linenumber="46" name="rhs_V_11_cast" contextFuncName="Conv2D" moduleName="Conv2D" rtlName="rhs_V_11_cast_fu_619_p1" latency="0" BRAM="-1" DSP="-1" FF="-1" LUT="-1" fileDirectory="D:\code\git\HLS\HLS"><\/item>
<item  id="85" filename="../src/Conv2d/Conv2d.cpp" linenumber="46" name="rhs_V_2_cast1" contextFuncName="Conv2D" moduleName="Conv2D" rtlName="rhs_V_2_cast1_fu_622_p1" latency="0" BRAM="-1" DSP="-1" FF="-1" LUT="-1" fileDirectory="D:\code\git\HLS\HLS"><\/item>
<item  id="86" filename="../src/Conv2d/Conv2d.cpp" linenumber="46" name="rhs_V_2_cast" contextFuncName="Conv2D" moduleName="Conv2D" rtlName="rhs_V_2_cast_fu_625_p1" latency="0" BRAM="-1" DSP="-1" FF="-1" LUT="-1" fileDirectory="D:\code\git\HLS\HLS"><\/item>
<item  id="89" filename="../src/Conv2d/Conv2d.cpp" linenumber="29" name="tmp_10" contextFuncName="Conv2D" moduleName="Conv2D" rtlName="tmp_10_fu_634_p1" latency="0" BRAM="-1" DSP="-1" FF="-1" LUT="-1" fileDirectory="D:\code\git\HLS\HLS"><\/item>
<item  id="95" filename="../src/Conv2d/Conv2d.cpp" linenumber="51" name="i_op_assign_cast14_c" contextFuncName="Conv2D" moduleName="Conv2D" rtlName="tmp_8_fu_1006_p00" latency="0" BRAM="-1" DSP="-1" FF="-1" LUT="-1" fileDirectory="D:\code\git\HLS\HLS"><\/item>
<item  id="96" filename="../src/Conv2d/Conv2d.cpp" linenumber="32" name="exitcond3" contextFuncName="Conv2D" moduleName="Conv2D" rtlName="exitcond3_fu_647_p2" latency="0" BRAM="-1" DSP="-1" FF="0" LUT="7" fileDirectory="D:\code\git\HLS\HLS"><\/item>
<item  id="98" filename="../src/Conv2d/Conv2d.cpp" linenumber="32" name="oc" contextFuncName="Conv2D" moduleName="Conv2D" rtlName="oc_fu_652_p2" latency="0" BRAM="-1" DSP="-1" FF="0" LUT="16" fileDirectory="D:\code\git\HLS\HLS"><\/item>
<item  id="101" filename="../src/Conv2d/Conv2d.cpp" linenumber="51" name="tmp_8" contextFuncName="Conv2D" moduleName="Conv2D" rtlName="Conv2D_mul_mul_16cud_U3" latency="0" BRAM="-1" DSP="-1" FF="-1" LUT="-1" fileDirectory="D:\code\git\HLS\HLS"><\/item>
<item  id="102" filename="../src/Conv2d/Conv2d.cpp" linenumber="51" name="tmp_1_cast1" contextFuncName="Conv2D" moduleName="Conv2D" rtlName="tmp_1_cast1_fu_658_p1" latency="0" BRAM="-1" DSP="-1" FF="-1" LUT="-1" fileDirectory="D:\code\git\HLS\HLS"><\/item>
<item  id="103" filename="../src/Conv2d/Conv2d.cpp" linenumber="51" name="biases_V6_sum" contextFuncName="Conv2D" moduleName="Conv2D" rtlName="biases_V6_sum_fu_662_p2" latency="0" BRAM="-1" DSP="-1" FF="0" LUT="32" fileDirectory="D:\code\git\HLS\HLS"><\/item>
<item  id="104" filename="../src/Conv2d/Conv2d.cpp" linenumber="51" name="biases_V6_sum_cast" contextFuncName="Conv2D" moduleName="Conv2D" rtlName="biases_V6_sum_cast_fu_667_p1" latency="0" BRAM="-1" DSP="-1" FF="-1" LUT="-1" fileDirectory="D:\code\git\HLS\HLS"><\/item>
<item  id="106" filename="../src/Conv2d/Conv2d.cpp" linenumber="45" name="lhs_V_11_cast" contextFuncName="Conv2D" moduleName="Conv2D" rtlName="ret_V_3_fu_681_p10" latency="0" BRAM="-1" DSP="-1" FF="-1" LUT="-1" fileDirectory="D:\code\git\HLS\HLS"><\/item>
<item  id="107" filename="../src/Conv2d/Conv2d.cpp" linenumber="45" name="ret_V_3" contextFuncName="Conv2D" moduleName="Conv2D" rtlName="ret_V_3_fu_681_p2" latency="0" BRAM="-1" DSP="2" FF="0" LUT="21" fileDirectory="D:\code\git\HLS\HLS"><\/item>
<item  id="108" filename="../src/Conv2d/Conv2d.cpp" linenumber="45" name="lhs_V_2_cast" contextFuncName="Conv2D" moduleName="Conv2D" rtlName="ret_V_4_fu_689_p10" latency="0" BRAM="-1" DSP="-1" FF="-1" LUT="-1" fileDirectory="D:\code\git\HLS\HLS"><\/item>
<item  id="109" filename="../src/Conv2d/Conv2d.cpp" linenumber="45" name="ret_V_4" contextFuncName="Conv2D" moduleName="Conv2D" rtlName="ret_V_4_fu_689_p2" latency="0" BRAM="-1" DSP="2" FF="0" LUT="29" fileDirectory="D:\code\git\HLS\HLS"><\/item>
<item  id="114" filename="../src/Conv2d/Conv2d.cpp" linenumber="42" name="phi_mul20_cast" contextFuncName="Conv2D" moduleName="Conv2D" rtlName="phi_mul20_cast_fu_694_p1" latency="0" BRAM="-1" DSP="-1" FF="-1" LUT="-1" fileDirectory="D:\code\git\HLS\HLS"><\/item>
<item  id="115" filename="../src/Conv2d/Conv2d.cpp" linenumber="42" name="next_mul2" contextFuncName="Conv2D" moduleName="Conv2D" rtlName="next_mul2_fu_698_p2" latency="0" BRAM="-1" DSP="-1" FF="0" LUT="19" fileDirectory="D:\code\git\HLS\HLS"><\/item>
<item  id="116" filename="../src/Conv2d/Conv2d.cpp" linenumber="33" name="i_op_assign_4_cast1" contextFuncName="Conv2D" moduleName="Conv2D" rtlName="i_op_assign_4_cast1_fu_703_p1" latency="0" BRAM="-1" DSP="-1" FF="-1" LUT="-1" fileDirectory="D:\code\git\HLS\HLS"><\/item>
<item  id="117" filename="../src/Conv2d/Conv2d.cpp" linenumber="33" name="i_op_assign_4_cast" contextFuncName="Conv2D" moduleName="Conv2D" rtlName="i_op_assign_4_cast_fu_707_p1" latency="0" BRAM="-1" DSP="-1" FF="-1" LUT="-1" fileDirectory="D:\code\git\HLS\HLS"><\/item>
<item  id="118" filename="../src/Conv2d/Conv2d.cpp" linenumber="33" name="tmp_2" contextFuncName="Conv2D" moduleName="Conv2D" rtlName="tmp_2_fu_711_p2" latency="0" BRAM="-1" DSP="-1" FF="0" LUT="6" fileDirectory="D:\code\git\HLS\HLS"><\/item>
<item  id="120" filename="../src/Conv2d/Conv2d.cpp" linenumber="33" name="oh" contextFuncName="Conv2D" moduleName="Conv2D" rtlName="oh_fu_716_p2" latency="0" BRAM="-1" DSP="-1" FF="0" LUT="12" fileDirectory="D:\code\git\HLS\HLS"><\/item>
<item  id="123" filename="../src/Conv2d/Conv2d.cpp" linenumber="39" name="tmp_4" contextFuncName="Conv2D" moduleName="Conv2D" rtlName="tmp_4_fu_754_p2" latency="0" BRAM="-1" DSP="-1" FF="0" LUT="20" fileDirectory="D:\code\git\HLS\HLS"><\/item>
<item  id="124" filename="../src/Conv2d/Conv2d.cpp" linenumber="51" name="tmp_5" contextFuncName="Conv2D" moduleName="Conv2D" rtlName="tmp_5_fu_722_p2" latency="0" BRAM="-1" DSP="-1" FF="0" LUT="28" fileDirectory="D:\code\git\HLS\HLS"><\/item>
<item  id="126" filename="../src/Conv2d/Conv2d.cpp" linenumber="51" name="tmp_7" contextFuncName="Conv2D" moduleName="Conv2D" rtlName="tmp_7_fu_731_p2" latency="0" BRAM="-1" DSP="2" FF="0" LUT="37" fileDirectory="D:\code\git\HLS\HLS"><\/item>
<item  id="127" filename="../src/Conv2d/Conv2d.cpp" linenumber="51" name="tmp_10_cast" contextFuncName="Conv2D" moduleName="Conv2D" rtlName="tmp_10_cast_fu_736_p1" latency="0" BRAM="-1" DSP="-1" FF="-1" LUT="-1" fileDirectory="D:\code\git\HLS\HLS"><\/item>
<item  id="128" filename="../src/Conv2d/Conv2d.cpp" linenumber="51" name="out_data_V8_sum" contextFuncName="Conv2D" moduleName="Conv2D" rtlName="out_data_V8_sum_fu_739_p2" latency="0" BRAM="-1" DSP="-1" FF="0" LUT="33" fileDirectory="D:\code\git\HLS\HLS"><\/item>
<item  id="129" filename="../src/Conv2d/Conv2d.cpp" linenumber="51" name="out_data_V8_sum_cast" contextFuncName="Conv2D" moduleName="Conv2D" rtlName="out_data_V8_sum_cast_fu_744_p1" latency="0" BRAM="-1" DSP="-1" FF="-1" LUT="-1" fileDirectory="D:\code\git\HLS\HLS"><\/item>
<item  id="136" filename="../src/Conv2d/Conv2d.cpp" linenumber="42" name="phi_mul17_cast" contextFuncName="Conv2D" moduleName="Conv2D" rtlName="phi_mul17_cast_fu_758_p1" latency="0" BRAM="-1" DSP="-1" FF="-1" LUT="-1" fileDirectory="D:\code\git\HLS\HLS"><\/item>
<item  id="137" filename="../src/Conv2d/Conv2d.cpp" linenumber="42" name="next_mul3" contextFuncName="Conv2D" moduleName="Conv2D" rtlName="next_mul3_fu_762_p2" latency="0" BRAM="-1" DSP="-1" FF="0" LUT="19" fileDirectory="D:\code\git\HLS\HLS"><\/item>
<item  id="138" filename="../src/Conv2d/Conv2d.cpp" linenumber="34" name="i_op_assign_5_cast" contextFuncName="Conv2D" moduleName="Conv2D" rtlName="i_op_assign_5_cast_fu_767_p1" latency="0" BRAM="-1" DSP="-1" FF="-1" LUT="-1" fileDirectory="D:\code\git\HLS\HLS"><\/item>
<item  id="139" filename="../src/Conv2d/Conv2d.cpp" linenumber="34" name="tmp_11" contextFuncName="Conv2D" moduleName="Conv2D" rtlName="tmp_11_fu_771_p2" latency="0" BRAM="-1" DSP="-1" FF="0" LUT="6" fileDirectory="D:\code\git\HLS\HLS"><\/item>
<item  id="141" filename="../src/Conv2d/Conv2d.cpp" linenumber="34" name="ow" contextFuncName="Conv2D" moduleName="Conv2D" rtlName="ow_fu_776_p2" latency="0" BRAM="-1" DSP="-1" FF="0" LUT="12" fileDirectory="D:\code\git\HLS\HLS"><\/item>
<item  id="144" filename="../src/Conv2d/Conv2d.cpp" linenumber="40" name="tmp_12" contextFuncName="Conv2D" moduleName="Conv2D" rtlName="tmp_12_fu_782_p2" latency="0" BRAM="-1" DSP="-1" FF="0" LUT="20" fileDirectory="D:\code\git\HLS\HLS"><\/item>
<item  id="151" filename="../src/Conv2d/Conv2d.cpp" linenumber="46" name="next_mul4" contextFuncName="Conv2D" moduleName="Conv2D" rtlName="next_mul4_fu_787_p2" latency="0" BRAM="-1" DSP="-1" FF="0" LUT="24" fileDirectory="D:\code\git\HLS\HLS"><\/item>
<item  id="152" filename="../src/Conv2d/Conv2d.cpp" linenumber="44" name="next_mul5" contextFuncName="Conv2D" moduleName="Conv2D" rtlName="next_mul5_fu_792_p2" latency="0" BRAM="-1" DSP="-1" FF="0" LUT="24" fileDirectory="D:\code\git\HLS\HLS"><\/item>
<item  id="153" filename="../src/Conv2d/Conv2d.cpp" linenumber="36" name="exitcond1" contextFuncName="Conv2D" moduleName="Conv2D" rtlName="exitcond1_fu_797_p2" latency="0" BRAM="-1" DSP="-1" FF="0" LUT="7" fileDirectory="D:\code\git\HLS\HLS"><\/item>
<item  id="155" filename="../src/Conv2d/Conv2d.cpp" linenumber="36" name="ic" contextFuncName="Conv2D" moduleName="Conv2D" rtlName="ic_fu_802_p2" latency="0" BRAM="-1" DSP="-1" FF="0" LUT="16" fileDirectory="D:\code\git\HLS\HLS"><\/item>
<item  id="158" filename="../src/Conv2d/Conv2d.cpp" linenumber="44" name="lhs_V_5_cast" contextFuncName="Conv2D" moduleName="Conv2D" rtlName="ret_V_7_fu_1011_p00" latency="0" BRAM="-1" DSP="-1" FF="-1" LUT="-1" fileDirectory="D:\code\git\HLS\HLS"><\/item>
<item  id="159" filename="../src/Conv2d/Conv2d.cpp" linenumber="44" name="ret_V_7" contextFuncName="Conv2D" moduleName="Conv2D" rtlName="Conv2D_mul_mul_24dEe_U4" latency="0" BRAM="-1" DSP="-1" FF="-1" LUT="-1" fileDirectory="D:\code\git\HLS\HLS"><\/item>
<item  id="160" filename="../src/Conv2d/Conv2d.cpp" linenumber="45" name="lhs_V_7_cast" contextFuncName="Conv2D" moduleName="Conv2D" rtlName="lhs_V_7_cast_fu_812_p1" latency="0" BRAM="-1" DSP="-1" FF="-1" LUT="-1" fileDirectory="D:\code\git\HLS\HLS"><\/item>
<item  id="161" filename="../src/Conv2d/Conv2d.cpp" linenumber="46" name="lhs_V_3_cast" contextFuncName="Conv2D" moduleName="Conv2D" rtlName="grp_fu_1017_p00" latency="0" BRAM="-1" DSP="-1" FF="-1" LUT="-1" fileDirectory="D:\code\git\HLS\HLS"><\/item>
<item  id="162" filename="../src/Conv2d/Conv2d.cpp" linenumber="46" name="ret_V_6" contextFuncName="Conv2D" moduleName="Conv2D" rtlName="Conv2D_mac_muladdeOg_U5" latency="0" BRAM="-1" DSP="-1" FF="-1" LUT="-1" fileDirectory="D:\code\git\HLS\HLS"><\/item>
<item  id="163" filename="../src/Conv2d/Conv2d.cpp" linenumber="46" name="ret_V_6_cast" contextFuncName="Conv2D" moduleName="Conv2D" rtlName="Conv2D_mac_muladdeOg_U5" latency="0" BRAM="-1" DSP="-1" FF="-1" LUT="-1" fileDirectory="D:\code\git\HLS\HLS"><\/item>
<item  id="164" filename="../src/Conv2d/Conv2d.cpp" linenumber="46" name="tmp2" contextFuncName="Conv2D" moduleName="Conv2D" rtlName="Conv2D_mac_muladdeOg_U5" latency="0" BRAM="-1" DSP="-1" FF="-1" LUT="-1" fileDirectory="D:\code\git\HLS\HLS"><\/item>
<item  id="170" filename="../src/Conv2d/Conv2d.cpp" linenumber="46" name="next_mul" contextFuncName="Conv2D" moduleName="Conv2D" rtlName="next_mul_fu_819_p2" latency="0" BRAM="-1" DSP="-1" FF="0" LUT="16" fileDirectory="D:\code\git\HLS\HLS"><\/item>
<item  id="171" filename="../src/Conv2d/Conv2d.cpp" linenumber="37" name="i_op_assign_2_cast7" contextFuncName="Conv2D" moduleName="Conv2D" rtlName="i_op_assign_2_cast7_fu_824_p1" latency="0" BRAM="-1" DSP="-1" FF="-1" LUT="-1" fileDirectory="D:\code\git\HLS\HLS"><\/item>
<item  id="172" filename="../src/Conv2d/Conv2d.cpp" linenumber="37" name="exitcond2" contextFuncName="Conv2D" moduleName="Conv2D" rtlName="exitcond2_fu_828_p2" latency="0" BRAM="-1" DSP="-1" FF="0" LUT="4" fileDirectory="D:\code\git\HLS\HLS"><\/item>
<item  id="174" filename="../src/Conv2d/Conv2d.cpp" linenumber="37" name="kh" contextFuncName="Conv2D" moduleName="Conv2D" rtlName="kh_fu_833_p2" latency="0" BRAM="-1" DSP="-1" FF="0" LUT="8" fileDirectory="D:\code\git\HLS\HLS"><\/item>
<item  id="177" filename="../src/Conv2d/Conv2d.cpp" linenumber="39" name="ih" contextFuncName="Conv2D" moduleName="Conv2D" rtlName="ih_fu_839_p2" latency="0" BRAM="-1" DSP="-1" FF="0" LUT="20" fileDirectory="D:\code\git\HLS\HLS"><\/item>
<item  id="178" filename="../src/Conv2d/Conv2d.cpp" linenumber="42" name="tmp_13" contextFuncName="Conv2D" moduleName="Conv2D" rtlName="tmp_13_reg_1358" latency="0" BRAM="-1" DSP="-1" FF="-1" LUT="-1" fileDirectory="D:\code\git\HLS\HLS"><\/item>
<item  id="179" filename="../src/Conv2d/Conv2d.cpp" linenumber="42" name="tmp_14" contextFuncName="Conv2D" moduleName="Conv2D" rtlName="tmp_14_fu_852_p2" latency="0" BRAM="-1" DSP="-1" FF="0" LUT="8" fileDirectory="D:\code\git\HLS\HLS"><\/item>
<item  id="181" filename="../src/Conv2d/Conv2d.cpp" linenumber="44" name="ret_V_8" contextFuncName="Conv2D" moduleName="Conv2D" rtlName="Conv2D_mac_muladdfYi_U6" latency="0" BRAM="-1" DSP="-1" FF="-1" LUT="-1" fileDirectory="D:\code\git\HLS\HLS"><\/item>
<item  id="182" filename="../src/Conv2d/Conv2d.cpp" linenumber="45" name="rhs_V_6_cast" contextFuncName="Conv2D" moduleName="Conv2D" rtlName="Conv2D_mac_muladdfYi_U6" latency="0" BRAM="-1" DSP="-1" FF="-1" LUT="-1" fileDirectory="D:\code\git\HLS\HLS"><\/item>
<item  id="183" filename="../src/Conv2d/Conv2d.cpp" linenumber="45" name="ret_V_s" contextFuncName="Conv2D" moduleName="Conv2D" rtlName="Conv2D_mac_muladdfYi_U6" latency="0" BRAM="-1" DSP="-1" FF="-1" LUT="-1" fileDirectory="D:\code\git\HLS\HLS"><\/item>
<item  id="188" filename="../src/Conv2d/Conv2d.cpp" linenumber="38" name="i_op_assign_3_cast5" contextFuncName="Conv2D" moduleName="Conv2D" rtlName="i_op_assign_3_cast5_fu_861_p1" latency="0" BRAM="-1" DSP="-1" FF="-1" LUT="-1" fileDirectory="D:\code\git\HLS\HLS"><\/item>
<item  id="189" filename="../src/Conv2d/Conv2d.cpp" linenumber="38" name="exitcond" contextFuncName="Conv2D" moduleName="Conv2D" rtlName="exitcond_fu_865_p2" latency="0" BRAM="-1" DSP="-1" FF="0" LUT="4" fileDirectory="D:\code\git\HLS\HLS"><\/item>
<item  id="191" filename="../src/Conv2d/Conv2d.cpp" linenumber="38" name="kw" contextFuncName="Conv2D" moduleName="Conv2D" rtlName="kw_fu_870_p2" latency="0" BRAM="-1" DSP="-1" FF="0" LUT="8" fileDirectory="D:\code\git\HLS\HLS"><\/item>
<item  id="194" filename="../src/Conv2d/Conv2d.cpp" linenumber="40" name="iw" contextFuncName="Conv2D" moduleName="Conv2D" rtlName="iw_fu_876_p2" latency="0" BRAM="-1" DSP="-1" FF="0" LUT="20" fileDirectory="D:\code\git\HLS\HLS"><\/item>
<item  id="195" filename="../src/Conv2d/Conv2d.cpp" linenumber="40" name="iw_cast" contextFuncName="Conv2D" moduleName="Conv2D" rtlName="iw_cast_fu_881_p1" latency="0" BRAM="-1" DSP="-1" FF="-1" LUT="-1" fileDirectory="D:\code\git\HLS\HLS"><\/item>
<item  id="198" filename="../src/Conv2d/Conv2d.cpp" linenumber="42" name="tmp_15" contextFuncName="Conv2D" moduleName="Conv2D" rtlName="tmp_15_fu_885_p3" latency="0" BRAM="-1" DSP="-1" FF="-1" LUT="-1" fileDirectory="D:\code\git\HLS\HLS"><\/item>
<item  id="199" filename="../src/Conv2d/Conv2d.cpp" linenumber="42" name="rev" contextFuncName="Conv2D" moduleName="Conv2D" rtlName="rev_fu_893_p2" latency="0" BRAM="-1" DSP="-1" FF="0" LUT="2" fileDirectory="D:\code\git\HLS\HLS"><\/item>
<item  id="200" filename="../src/Conv2d/Conv2d.cpp" linenumber="42" name="tmp_16" contextFuncName="Conv2D" moduleName="Conv2D" rtlName="tmp_16_fu_899_p2" latency="0" BRAM="-1" DSP="-1" FF="0" LUT="8" fileDirectory="D:\code\git\HLS\HLS"><\/item>
<item  id="201" filename="../src/Conv2d/Conv2d.cpp" linenumber="42" name="tmp1" contextFuncName="Conv2D" moduleName="Conv2D" rtlName="tmp1_fu_904_p2" latency="0" BRAM="-1" DSP="-1" FF="0" LUT="1" fileDirectory="D:\code\git\HLS\HLS"><\/item>
<item  id="202" filename="../src/Conv2d/Conv2d.cpp" linenumber="42" name="or_cond5" contextFuncName="Conv2D" moduleName="Conv2D" rtlName="or_cond5_fu_910_p2" latency="0" BRAM="-1" DSP="-1" FF="0" LUT="1" fileDirectory="D:\code\git\HLS\HLS"><\/item>
<item  id="205" filename="../src/Conv2d/Conv2d.cpp" linenumber="45" name="rhs_V_7_cast" contextFuncName="Conv2D" moduleName="Conv2D" rtlName="rhs_V_7_cast_fu_915_p1" latency="0" BRAM="-1" DSP="-1" FF="-1" LUT="-1" fileDirectory="D:\code\git\HLS\HLS"><\/item>
<item  id="206" filename="../src/Conv2d/Conv2d.cpp" linenumber="45" name="ret_V_9" contextFuncName="Conv2D" moduleName="Conv2D" rtlName="ret_V_9_fu_919_p2" latency="0" BRAM="-1" DSP="-1" FF="0" LUT="33" fileDirectory="D:\code\git\HLS\HLS"><\/item>
<item  id="207" filename="../src/Conv2d/Conv2d.cpp" linenumber="46" name="tmp_29_cast" contextFuncName="Conv2D" moduleName="Conv2D" rtlName="tmp_29_cast_fu_924_p1" latency="0" BRAM="-1" DSP="-1" FF="-1" LUT="-1" fileDirectory="D:\code\git\HLS\HLS"><\/item>
<item  id="208" filename="../src/Conv2d/Conv2d.cpp" linenumber="46" name="tmp3" contextFuncName="Conv2D" moduleName="Conv2D" rtlName="tmp3_fu_928_p2" latency="0" BRAM="-1" DSP="-1" FF="0" LUT="16" fileDirectory="D:\code\git\HLS\HLS"><\/item>
<item  id="209" filename="../src/Conv2d/Conv2d.cpp" linenumber="46" name="tmp3_cast" contextFuncName="Conv2D" moduleName="Conv2D" rtlName="tmp3_cast_fu_934_p1" latency="0" BRAM="-1" DSP="-1" FF="-1" LUT="-1" fileDirectory="D:\code\git\HLS\HLS"><\/item>
<item  id="210" filename="../src/Conv2d/Conv2d.cpp" linenumber="46" name="tmp_17" contextFuncName="Conv2D" moduleName="Conv2D" rtlName="tmp_17_fu_938_p2" latency="0" BRAM="-1" DSP="-1" FF="0" LUT="48" fileDirectory="D:\code\git\HLS\HLS"><\/item>
<item  id="211" filename="../src/Conv2d/Conv2d.cpp" linenumber="46" name="tmp_32_cast_cast" contextFuncName="Conv2D" moduleName="Conv2D" rtlName="tmp_32_cast_cast_fu_943_p1" latency="0" BRAM="-1" DSP="-1" FF="-1" LUT="-1" fileDirectory="D:\code\git\HLS\HLS"><\/item>
<item  id="212" filename="../src/Conv2d/Conv2d.cpp" linenumber="46" name="in_data_V2_sum" contextFuncName="Conv2D" moduleName="Conv2D" rtlName="in_data_V2_sum_fu_947_p2" latency="0" BRAM="-1" DSP="-1" FF="0" LUT="33" fileDirectory="D:\code\git\HLS\HLS"><\/item>
<item  id="213" filename="../src/Conv2d/Conv2d.cpp" linenumber="46" name="in_data_V2_sum_cast" contextFuncName="Conv2D" moduleName="Conv2D" rtlName="in_data_V2_sum_cast_fu_952_p1" latency="0" BRAM="-1" DSP="-1" FF="-1" LUT="-1" fileDirectory="D:\code\git\HLS\HLS"><\/item>
<item  id="218" filename="../src/Conv2d/Conv2d.cpp" linenumber="46" name="weights_V4_sum" contextFuncName="Conv2D" moduleName="Conv2D" rtlName="weights_V4_sum_fu_962_p2" latency="0" BRAM="-1" DSP="-1" FF="0" LUT="49" fileDirectory="D:\code\git\HLS\HLS"><\/item>
<item  id="219" filename="../src/Conv2d/Conv2d.cpp" linenumber="46" name="weights_V4_sum_cast" contextFuncName="Conv2D" moduleName="Conv2D" rtlName="weights_V4_sum_cast_fu_967_p1" latency="0" BRAM="-1" DSP="-1" FF="-1" LUT="-1" fileDirectory="D:\code\git\HLS\HLS"><\/item>
<item  id="224" filename="../src/Conv2d/Conv2d.cpp" linenumber="46" name="r_V_2" contextFuncName="Conv2D" moduleName="Conv2D" rtlName="Conv2D_mac_muladdg8j_U7" latency="0" BRAM="-1" DSP="-1" FF="-1" LUT="-1" fileDirectory="D:\code\git\HLS\HLS"><\/item>
<item  id="225" filename="../src/Conv2d/Conv2d.cpp" linenumber="46" name="lhs_V_2" contextFuncName="Conv2D" moduleName="Conv2D" rtlName="grp_fu_1029_p2" latency="0" BRAM="-1" DSP="-1" FF="-1" LUT="-1" fileDirectory="D:\code\git\HLS\HLS"><\/item>
<item  id="226" filename="../src/Conv2d/Conv2d.cpp" linenumber="46" name="ret_V_14" contextFuncName="Conv2D" moduleName="Conv2D" rtlName="Conv2D_mac_muladdg8j_U7" latency="0" BRAM="-1" DSP="-1" FF="-1" LUT="-1" fileDirectory="D:\code\git\HLS\HLS"><\/item>
<item  id="227" filename="../src/Conv2d/Conv2d.cpp" linenumber="46" name="sum_V" contextFuncName="Conv2D" moduleName="Conv2D" rtlName="p_Val2_2_be_reg_420" latency="0" BRAM="-1" DSP="-1" FF="-1" LUT="-1" fileDirectory="D:\code\git\HLS\HLS"><\/item>
<item  id="239" filename="../src/Conv2d/Conv2d.cpp" linenumber="51" name="addconv" contextFuncName="Conv2D" moduleName="Conv2D" rtlName="addconv_fu_1001_p2" latency="0" BRAM="-1" DSP="-1" FF="0" LUT="16" fileDirectory="D:\code\git\HLS\HLS"><\/item>
<\/annotationInfo>
</annotationInfo>
